aiida_worktree/__init__.py
aiida_worktree/decorator.py
aiida_worktree/node.py
aiida_worktree/property.py
aiida_worktree/socket.py
aiida_worktree/worktree.py
aiida_worktree/cli/__init__.py
aiida_worktree/cli/cmd_tree.py
aiida_worktree/cli/cmd_web.py
aiida_worktree/cli/cmd_worktree.py
aiida_worktree/cli/query_worktree.py
aiida_worktree/engine/__init__.py
aiida_worktree/engine/worktree.py
aiida_worktree/executors/__init__.py
aiida_worktree/executors/builtin.py
aiida_worktree/executors/qe.py
aiida_worktree/executors/test.py
aiida_worktree/nodes/__init__.py
aiida_worktree/nodes/builtin.py
aiida_worktree/nodes/qe.py
aiida_worktree/nodes/test.py
aiida_worktree/orm/worktree.py
aiida_worktree/properties/__init__.py
aiida_worktree/properties/built_in.py
aiida_worktree/sockets/__init__.py
aiida_worktree/sockets/built_in.py
aiida_worktree/utils/__init__.py
aiida_worktree/utils/analysis.py
aiida_worktree/utils/tree.py
aiida_worktree/web/README.md
aiida_worktree/web/backend/main.py
aiida_worktree/web/backend/app/__init__.py
aiida_worktree/web/backend/app/api.py
aiida_worktree/web/backend/app/daemon.py
aiida_worktree/web/backend/app/datanode.py
aiida_worktree/web/backend/app/utils.py
aiida_worktree/web/backend/app/worktree.py
aiida_worktree/web/frontend/.gitignore
aiida_worktree/web/frontend/.rete-patch
aiida_worktree/web/frontend/README.md
aiida_worktree/web/frontend/package-lock.json
aiida_worktree/web/frontend/package.json
aiida_worktree/web/frontend/tsconfig.json
aiida_worktree/web/frontend/build/asset-manifest.json
aiida_worktree/web/frontend/build/favicon.ico
aiida_worktree/web/frontend/build/index.html
aiida_worktree/web/frontend/build/manifest.json
aiida_worktree/web/frontend/build/robots.txt
aiida_worktree/web/frontend/build/static/css/main.1cbd6711.css
aiida_worktree/web/frontend/build/static/css/main.1cbd6711.css.map
aiida_worktree/web/frontend/build/static/js/787.10122f11.chunk.js
aiida_worktree/web/frontend/build/static/js/787.10122f11.chunk.js.map
aiida_worktree-0.1.8.dist-info/entry_points.txt
aiida_worktree-0.1.8.dist-info/LICENSE
aiida_worktree-0.1.8.dist-info/WHEEL
aiida_worktree-0.1.8.dist-info/METADATA
aiida_worktree-0.1.8.dist-info/RECORD
